utensor_cgen/__init__.py
utensor_cgen/__main__.py
utensor_cgen/_extensions.py
utensor_cgen/cli.py
utensor_cgen/logger.py
utensor_cgen/utils.py
utensor_cgen/backend/__init__.py
utensor_cgen/backend/api.py
utensor_cgen/backend/base.py
utensor_cgen/backend/utensor/__init__.py
utensor_cgen/backend/utensor/_backend_impl.py
utensor_cgen/backend/utensor/_code_generator.py
utensor_cgen/backend/utensor/_graph_lower.py
utensor_cgen/backend/utensor/_operators.py
utensor_cgen/backend/utensor/snippets/__init__.py
utensor_cgen/backend/utensor/snippets/_base.py
utensor_cgen/backend/utensor/snippets/_snippets.py
utensor_cgen/backend/utensor/snippets/_types.py
utensor_cgen/backend/utensor/snippets/composer.py
utensor_cgen/backend/utensor/snippets/template_env.py
utensor_cgen/backend/utensor/snippets/templates/containers/get_ctx.cpp
utensor_cgen/backend/utensor/snippets/templates/containers/weight_header.hpp
utensor_cgen/backend/utensor/snippets/templates/snippets/add_op.cpp
utensor_cgen/backend/utensor/snippets/templates/snippets/argmax_op.cpp
utensor_cgen/backend/utensor/snippets/templates/snippets/cmsis_nn_fc_op.cpp
utensor_cgen/backend/utensor/snippets/templates/snippets/cmsis_uint8q7origin_op.cpp
utensor_cgen/backend/utensor/snippets/templates/snippets/comments.cpp
utensor_cgen/backend/utensor/snippets/templates/snippets/conv2d_op.cpp
utensor_cgen/backend/utensor/snippets/templates/snippets/create_tensor_binary.cpp
utensor_cgen/backend/utensor/snippets/templates/snippets/create_tensor_idx.cpp
utensor_cgen/backend/utensor/snippets/templates/snippets/create_tensor_new.cpp
utensor_cgen/backend/utensor/snippets/templates/snippets/dequantize_op.cpp
utensor_cgen/backend/utensor/snippets/templates/snippets/fused_conv2d_maxpool_op.cpp
utensor_cgen/backend/utensor/snippets/templates/snippets/gather_op.cpp
utensor_cgen/backend/utensor/snippets/templates/snippets/get_ctx.hpp
utensor_cgen/backend/utensor/snippets/templates/snippets/matmul_op.cpp
utensor_cgen-0.4.2.dist-info/LICENSE
utensor_cgen-0.4.2.dist-info/METADATA
utensor_cgen-0.4.2.dist-info/WHEEL
utensor_cgen-0.4.2.dist-info/entry_points.txt
utensor_cgen-0.4.2.dist-info/top_level.txt
utensor_cgen-0.4.2.dist-info/RECORD
