Metadata-Version: 2.1
Name: utensor-cgen
Version: 0.4.2
Summary: C code generation program for uTensor
Home-page: https://github.com/uTensor/utensor_cgen
Author: Dboy Liao
Author-email: qmalliao@gmail.com
License: Apache License
Requires-Dist: Jinja2
Requires-Dist: tensorflow (==1.13.1)
Requires-Dist: idx2numpy
Requires-Dist: attrs
Requires-Dist: click
Requires-Dist: torch
Requires-Dist: torchvision
Requires-Dist: onnx-tf (==1.2.1)
Requires-Dist: graphviz
Requires-Dist: toml
Provides-Extra: dev
Requires-Dist: pytest ; extra == 'dev'
